autoreg.py
AutoReg_Mrpac6689-5.0.0.dist-info/LICENSE
AutoReg_Mrpac6689-5.0.0.dist-info/METADATA
AutoReg_Mrpac6689-5.0.0.dist-info/WHEEL
AutoReg_Mrpac6689-5.0.0.dist-info/entry_points.txt
AutoReg_Mrpac6689-5.0.0.dist-info/top_level.txt
AutoReg_Mrpac6689-5.0.0.dist-info/RECORD
