Metadata-Version: 2.1
Name: AutoReg-Mrpac6689
Version: 5.0.0
Summary: AUTOREG - Operação automatizada de Sistemas - SISREG & G-HOSP
Home-page: https://github.com/Mrpac6689/AutoReg
Author: Michel Ribeiro Paes
Author-email: michelrpaes@gmail.com
License: GPL-3.0-or-later
Classifier: Programming Language :: Python :: 3
Classifier: License :: OSI Approved :: GNU General Public License v3 (GPLv3)
Classifier: Operating System :: OS Independent
Requires-Python: >=3
License-File: LICENSE
Requires-Dist: altgraph==0.17.4
Requires-Dist: attrs==24.2.0
Requires-Dist: beautifulsoup4==4.12.3
Requires-Dist: bs4==0.0.2
Requires-Dist: certifi==2024.8.30
Requires-Dist: cffi==1.17.1
Requires-Dist: charset-normalizer==3.4.0
Requires-Dist: configparser==7.1.0
Requires-Dist: h11==0.14.0
Requires-Dist: idna==3.10
Requires-Dist: numpy==2.1.3
Requires-Dist: outcome==1.3.0.post0
Requires-Dist: packaging==24.1
Requires-Dist: pandas==2.2.3
Requires-Dist: pathlib==1.0.1
Requires-Dist: pefile==2023.2.7
Requires-Dist: pillow==11.0.0
Requires-Dist: pycparser==2.22
Requires-Dist: PyGetWindow==0.0.9
Requires-Dist: pyinstaller==6.11.0
Requires-Dist: pyinstaller-hooks-contrib==2024.9
Requires-Dist: PyRect==0.2.0
Requires-Dist: PySocks==1.7.1
Requires-Dist: python-dateutil==2.9.0.post0
Requires-Dist: pytz==2024.2
Requires-Dist: pywin32-ctypes==0.2.3
Requires-Dist: requests==2.32.3
Requires-Dist: selenium==4.26.1
Requires-Dist: setuptools==75.3.0
Requires-Dist: six==1.16.0
Requires-Dist: sniffio==1.3.1
Requires-Dist: sortedcontainers==2.4.0
Requires-Dist: soupsieve==2.6
Requires-Dist: tk==0.1.0
Requires-Dist: trio==0.27.0
Requires-Dist: trio-websocket==0.11.1
Requires-Dist: typing-extensions==4.12.2
Requires-Dist: tzdata==2024.2
Requires-Dist: urllib3==2.2.3
Requires-Dist: websocket-client==1.8.0
Requires-Dist: wheel==0.44.0
Requires-Dist: wsproto==1.2.0
